power_supply_manager/__init__.py
power_supply_manager/app.py
power_supply_manager/demo_device.py
power_supply_manager/device.py
power_supply_manager/logger.py
power_supply_manager/state.py
power_supply_manager/test_plot.py
power_supply_manager-2.0.0.dist-info/LICENSE
power_supply_manager-2.0.0.dist-info/METADATA
power_supply_manager-2.0.0.dist-info/WHEEL
power_supply_manager-2.0.0.dist-info/entry_points.txt
power_supply_manager-2.0.0.dist-info/RECORD
