Metadata-Version: 2.1
Name: power-supply-manager
Version: 2.0.0
Summary: Power Supply Manager
License: MIT
Author: Willie Marchetto
Author-email: willie@devbuildzero.com
Requires-Python: >=3.8,<3.12
Classifier: License :: OSI Approved :: MIT License
Classifier: Programming Language :: Python :: 3
Classifier: Programming Language :: Python :: 3.8
Classifier: Programming Language :: Python :: 3.9
Classifier: Programming Language :: Python :: 3.10
Classifier: Programming Language :: Python :: 3.11
Requires-Dist: coloredlogs (>=15.0.1,<16.0.0)
Requires-Dist: dearpygui (==2.0.0)
Requires-Dist: matplotlib (>=3.6.0,<4.0.0)
Requires-Dist: pandas (>=2.0.1,<3.0.0)
Requires-Dist: pyinstaller (>=6.14.1,<7.0.0)
Requires-Dist: python-vxi11 (>=0.9,<0.10)
